code_sandbox_mcp/__init__.py
code_sandbox_mcp/server.py
code_sandbox_mcp-0.1.0.dist-info/METADATA
code_sandbox_mcp-0.1.0.dist-info/WHEEL
code_sandbox_mcp-0.1.0.dist-info/entry_points.txt
code_sandbox_mcp-0.1.0.dist-info/RECORD
