Metadata-Version: 2.4
Name: code-sandbox-mcp
Version: 0.1.0
Summary: MCP server for E2B code sandbox - Execute code and commands in secure E2B sandboxes
Project-URL: Homepage, https://github.com/feifeigood/code-sandbox-mcp
Project-URL: Documentation, https://github.com/feifeigood/code-sandbox-mcp#readme
Project-URL: Repository, https://github.com/feifeigood/code-sandbox-mcp
Project-URL: Issues, https://github.com/feifeigood/code-sandbox-mcp/issues
Author-email: PengFei Bai <feifeigood@gmail.com>
License: MIT
Keywords: code-execution,e2b,mcp,model-context-protocol,sandbox
Classifier: Development Status :: 4 - Beta
Classifier: Intended Audience :: Developers
Classifier: License :: OSI Approved :: MIT License
Classifier: Programming Language :: Python :: 3
Classifier: Programming Language :: Python :: 3.10
Classifier: Programming Language :: Python :: 3.11
Classifier: Programming Language :: Python :: 3.12
Requires-Python: >=3.10.0
Requires-Dist: e2b-code-interpreter>=2.4.1
Requires-Dist: mcp[cli]>=1.25.0
Requires-Dist: python-dotenv>=1.2.1
